ckanext_dc_log_view-1.0.0-py3.12-nspkg.pth
ckanext/dc_log_view/__init__.py
ckanext/dc_log_view/_version.py
ckanext/dc_log_view/plugin.py
ckanext/dc_log_view/assets/.gitignore
ckanext/dc_log_view/assets/dc_log_view.css
ckanext/dc_log_view/assets/webassets.yml
ckanext/dc_log_view/templates/.gitignore
ckanext/dc_log_view/templates/dc_view_log.html
ckanext/dc_log_view/tests/__init__.py
ckanext/dc_log_view/tests/requirements.txt
ckanext/dc_log_view/tests/test_plugin.py
ckanext/dc_log_view/tests/data/calibration_beads_47.rtdc
ckanext_dc_log_view-1.0.0.dist-info/licenses/LICENSE
ckanext_dc_log_view-1.0.0.dist-info/METADATA
ckanext_dc_log_view-1.0.0.dist-info/WHEEL
ckanext_dc_log_view-1.0.0.dist-info/entry_points.txt
ckanext_dc_log_view-1.0.0.dist-info/namespace_packages.txt
ckanext_dc_log_view-1.0.0.dist-info/top_level.txt
ckanext_dc_log_view-1.0.0.dist-info/RECORD
